pysr_abc_events/__init__.py
pysr_abc_events/dispatcher.py
pysr_abc_events/listener.py
pysr_abc_events/stoppable.py
pysr_abc_events-1.0.0.dist-info/METADATA
pysr_abc_events-1.0.0.dist-info/WHEEL
pysr_abc_events-1.0.0.dist-info/RECORD
