Metadata-Version: 2.3
Name: pysr-abc-events
Version: 1.0.0
Summary: 
Author: Alexey Volkov
Author-email: webwizardry@hotmail.com
Requires-Python: >=3.12,<4.0
Classifier: Programming Language :: Python :: 3
Classifier: Programming Language :: Python :: 3.12
Classifier: Programming Language :: Python :: 3.13
